ripple/FD_waveform.py
ripple/__init__.py
ripple/constants.py
ripple/noise.py
ripple/ripple.py
ripple/typing.py
ripple/noise_resources/O2_ASD.dat
ripple/noise_resources/O3a_Livingston_ASD.dat
ripple/noise_resources/__init__.py
ripple/noise_resources/aLIGO.dat
ripple/noise_resources/aLIGOZeroDetHighPower.dat
ripple/noise_resources/ce.dat
ripple/noise_resources/et.dat
ripple/waveforms/IMRPhenomD.py
ripple/waveforms/IMRPhenomD_NRTidalv2.py
ripple/waveforms/IMRPhenomD_QNMdata.py
ripple/waveforms/IMRPhenomD_utils.py
ripple/waveforms/IMRPhenomPv2.py
ripple/waveforms/IMRPhenomPv2_utils.py
ripple/waveforms/IMRPhenomXAS.py
ripple/waveforms/IMRPhenomX_utils.py
ripple/waveforms/IMRPhenom_tidal_utils.py
ripple/waveforms/TaylorF2.py
ripple/waveforms/__init__.py
ripplegw/FD_waveform.py
ripplegw/__init__.py
ripplegw/constants.py
ripplegw/noise.py
ripplegw/typing.py
ripplegw/noise_resources/O2_ASD.dat
ripplegw/noise_resources/O3a_Livingston_ASD.dat
ripplegw/noise_resources/__init__.py
ripplegw/noise_resources/aLIGO.dat
ripplegw/noise_resources/aLIGOZeroDetHighPower.dat
ripplegw/noise_resources/ce.dat
ripplegw/noise_resources/et.dat
ripplegw/waveforms/IMRPhenomD.py
ripplegw/waveforms/IMRPhenomD_NRTidalv2.py
ripplegw/waveforms/IMRPhenomD_QNMdata.py
ripplegw/waveforms/IMRPhenomD_utils.py
ripplegw/waveforms/IMRPhenomPv2.py
ripplegw/waveforms/IMRPhenomPv2_utils.py
ripplegw/waveforms/IMRPhenomXAS.py
ripplegw/waveforms/IMRPhenomX_utils.py
ripplegw/waveforms/IMRPhenom_tidal_utils.py
ripplegw/waveforms/TaylorF2.py
ripplegw/waveforms/__init__.py
ripplegw-0.0.9.dist-info/LICENSE
ripplegw-0.0.9.dist-info/METADATA
ripplegw-0.0.9.dist-info/WHEEL
ripplegw-0.0.9.dist-info/top_level.txt
ripplegw-0.0.9.dist-info/RECORD
