Metadata-Version: 2.1
Name: ripplegw
Version: 0.0.9
Summary: A small jax package for differentiable and fast gravitational wave data analysis.
Home-page: https://ripple.readthedocs.io/en/latest/
Project-URL: Bug Tracker, https://github.com/tedwards2412/ripple
Keywords: gravitational waves,jax
Classifier: Programming Language :: Python :: 3
Classifier: License :: OSI Approved :: MIT License
Classifier: Operating System :: OS Independent
Requires-Python: >=3.9
License-File: LICENSE
Requires-Dist: jax
Requires-Dist: jaxlib
Requires-Dist: numpy
